src/llm-to-corpus/chatgpt.py
src/llm-to-corpus/cli.py
src/llm-to-corpus/huggingface.py
src/llm-to-corpus/version.py
src/llm_to_corpus/bloom.py
src/llm_to_corpus/chatgpt.py
src/llm_to_corpus/cli.py
src/llm_to_corpus/huggingface-falcon.py
src/llm_to_corpus/huggingface.py
src/llm_to_corpus/models.py
src/llm_to_corpus/version.py
llm_to_corpus-0.0.3.dist-info/LICENSE
llm_to_corpus-0.0.3.dist-info/METADATA
llm_to_corpus-0.0.3.dist-info/WHEEL
llm_to_corpus-0.0.3.dist-info/entry_points.txt
llm_to_corpus-0.0.3.dist-info/top_level.txt
llm_to_corpus-0.0.3.dist-info/RECORD
