Metadata-Version: 2.1
Name: llm-to-corpus
Version: 0.0.3
Summary: Large language model to corpus
Home-page: https://github.com/jordimas/llm-to-corpus/
Author: Jordi Mas
Author-email: jmas@softcatala.org
License: MIT
Classifier: Programming Language :: Python :: 3.6
Classifier: Programming Language :: Python :: 3.7
Classifier: Programming Language :: Python :: 3.8
Classifier: Programming Language :: Python :: 3.9
Classifier: Programming Language :: Python :: 3.10
Classifier: Programming Language :: Python :: 3.11
License-File: LICENSE
Provides-Extra: dev
Requires-Dist: flake8 (==6.*) ; extra == 'dev'
Requires-Dist: black (==23.*) ; extra == 'dev'
Requires-Dist: nose2 ; extra == 'dev'
